django_agent/__init__.py
django_agent/apps.py
django_agent/decorators.py
django_agent/tests.py
django_agent/urls.py
django_agent/views.py
django_agent-1.0.1.dist-info/LICENSE
django_agent-1.0.1.dist-info/METADATA
django_agent-1.0.1.dist-info/WHEEL
django_agent-1.0.1.dist-info/top_level.txt
django_agent-1.0.1.dist-info/RECORD
